tair_openapi_mcp_server/__init__.py
tair_openapi_mcp_server/main.py
tair_openapi_mcp_server/version.py
tair_openapi_mcp_server/tools/__init__.py
tair_openapi_mcp_server/tools/account.py
tair_openapi_mcp_server/tools/create_instance.py
tair_openapi_mcp_server/tools/describe.py
tair_openapi_mcp_server/tools/security_ips.py
tair_openapi_mcp_server/utils/__init__.py
tair_openapi_mcp_server/utils/config.py
tair_openapi_mcp_server/utils/logging.py
tair_openapi_mcp_server/utils/openapi_client.py
tair_openapi_mcp_server/utils/server.py
alibabacloud_tair_openapi_mcp_server-0.1.2.dist-info/METADATA
alibabacloud_tair_openapi_mcp_server-0.1.2.dist-info/WHEEL
alibabacloud_tair_openapi_mcp_server-0.1.2.dist-info/entry_points.txt
alibabacloud_tair_openapi_mcp_server-0.1.2.dist-info/top_level.txt
alibabacloud_tair_openapi_mcp_server-0.1.2.dist-info/RECORD
