Metadata-Version: 2.4
Name: alibabacloud-tair-openapi-mcp-server
Version: 0.1.2
Summary: MCP server for managing Alibaba Cloud R-KVStore (Tair/Redis) via OpenAPI
Requires-Python: >=3.12
Requires-Dist: python-dotenv>=1.0
Requires-Dist: mcp>=1.0.0
Requires-Dist: click>=8.0.0
Requires-Dist: alibabacloud_tea_openapi>=0.3.8
Requires-Dist: alibabacloud_r_kvstore20150101==6.1.0
Requires-Dist: alibabacloud_vpc20160428>=3.0.0
